aquahawk_client/__init__.py
aquahawk_client/client.py
aquahawk_client/types.py
aquahawk_client-0.0.5.dist-info/LICENSE
aquahawk_client-0.0.5.dist-info/METADATA
aquahawk_client-0.0.5.dist-info/WHEEL
aquahawk_client-0.0.5.dist-info/RECORD
